powerchord/__init__.py
powerchord/cli.py
powerchord/config.py
powerchord/runner.py
powerchord-0.4.14.dist-info/WHEEL
powerchord-0.4.14.dist-info/entry_points.txt
powerchord-0.4.14.dist-info/METADATA
powerchord-0.4.14.dist-info/RECORD
