Metadata-Version: 2.4
Name: powerchord
Version: 0.4.14
Summary: Concurrent CLI task runner
Keywords: task runner,cli utility,concurrency
Author: Huib Piguillet
Author-email: Huib Piguillet <huib@proton.me>
License-Expression: MIT
Classifier: Intended Audience :: Developers
Classifier: Topic :: Utilities
Classifier: Topic :: Software Development :: Build Tools
Classifier: Programming Language :: Python :: 3
Classifier: Programming Language :: Python :: 3.14
Classifier: Programming Language :: Python :: 3 :: Only
Requires-Dist: based-utils
Requires-Dist: chili
Requires-Dist: gaffe
Requires-Dist: kleur
Requires-Python: >=3.14
Project-URL: Github, https://github.com/githuib/powerchord
Project-URL: PyPI, https://pypi.org/project/powerchord/
